{
    "files_compared_count": 2,
    "comparison_window_start_utc": "2026-07-23T14:13:22.794660+00:00",
    "comparison_window_end_utc": "2026-07-24T03:17:49.751114+00:00",
    "comparison_window_hours": 13.07,
    "old_unique_appids": 1199,
    "new_unique_appids": 1200,
    "common_app_count": 1196,
    "new_entry_count": 4,
    "dropped_entry_count": 3,
    "moved_up_count": 798,
    "moved_down_count": 141,
    "stable_count": 257,
    "upward_spike_count": 4,
    "downward_spike_count": 0,
    "price_changes_count": 2,
    "release_changes_count": 6,
    "biggest_upward_spike_appid": "4964110",
    "biggest_upward_spike_title": "Darkest Dungeon\u00ae: The Fire's Edge",
    "biggest_upward_spike_delta": 67,
    "biggest_downward_spike_appid": null,
    "biggest_downward_spike_title": null,
    "biggest_downward_spike_delta": 0
}