{
    "appid": "4442710",
    "game_title": "Spirit Dungeon",
    "safe_slug": "spirit_dungeon",
    "analysis_date_utc": "2026-06-22T17:26:54.332008+00:00",
    "spike_window_start": "2026-06-19T00:00:00+00:00",
    "spike_window_end": "2026-06-22T00:00:00+00:00",
    "extended_window_start": "2026-05-05T00:00:00+00:00",
    "extended_window_end": "2026-06-25T00:00:00+00:00",
    "dt_start": "2026-06-19 00:00:00+00:00",
    "dt_end": "2026-06-22 00:00:00+00:00",
    "ext_start": "2026-05-05 00:00:00+00:00",
    "ext_end": "2026-06-25 00:00:00+00:00",
    "window_inferred_fallback": false,
    "prev_rank": 2369,
    "curr_rank": 2228,
    "rank_delta": 141,
    "movement_score": 0,
    "is_new_entry": false,
    "changed_fields_detected": [],
    "input_diff_row": {
        "appid": 4442710,
        "title_old": "Spirit Dungeon",
        "curr_title": "Spirit Dungeon",
        "prev_rank": 2369,
        "curr_rank": 2228,
        "rank_delta": 141,
        "abs_rank_delta": 141,
        "movement_type": "up",
        "spike_type": "upward_spike",
        "price_text_old": "Unpriced (Coming Soon)",
        "price_text_new": "Unpriced (Coming Soon)",
        "price_changed": false,
        "release_text_old": "Jun 25, 2026",
        "release_text_new": "Jun 25, 2026",
        "release_changed": false
    }
}