{
    "files_compared_count": 2,
    "comparison_window_start_utc": "2026-06-20T04:11:35.896686+00:00",
    "comparison_window_end_utc": "2026-06-20T14:15:40.905869+00:00",
    "comparison_window_hours": 10.07,
    "old_unique_appids": 2549,
    "new_unique_appids": 2525,
    "common_app_count": 2520,
    "new_entry_count": 5,
    "dropped_entry_count": 29,
    "moved_up_count": 451,
    "moved_down_count": 1603,
    "stable_count": 466,
    "upward_spike_count": 56,
    "downward_spike_count": 0,
    "price_changes_count": 1,
    "release_changes_count": 2,
    "biggest_upward_spike_appid": "3908940",
    "biggest_upward_spike_title": "Inferno Protocol",
    "biggest_upward_spike_delta": 149,
    "biggest_downward_spike_appid": null,
    "biggest_downward_spike_title": null,
    "biggest_downward_spike_delta": 0
}